sl_shared_assets/__init__.py
sl_shared_assets/py.typed
sl_shared_assets/configuration/__init__.py
sl_shared_assets/configuration/configuration_utilities.py
sl_shared_assets/configuration/experiment_configuration.py
sl_shared_assets/configuration/mesoscope_configuration.py
sl_shared_assets/configuration/vr_configuration.py
sl_shared_assets/data_classes/__init__.py
sl_shared_assets/data_classes/dataset_data.py
sl_shared_assets/data_classes/processing_data.py
sl_shared_assets/data_classes/runtime_data.py
sl_shared_assets/data_classes/session_data.py
sl_shared_assets/data_classes/surgery_data.py
sl_shared_assets/data_processing/__init__.py
sl_shared_assets/data_processing/interpolation.py
sl_shared_assets/data_transfer/__init__.py
sl_shared_assets/data_transfer/checksum_tools.py
sl_shared_assets/data_transfer/transfer_tools.py
sl_shared_assets/interfaces/__init__.py
sl_shared_assets/interfaces/configure.py
sl_shared_assets/interfaces/mcp_server.py
sl_shared_assets-7.0.0.dist-info/METADATA
sl_shared_assets-7.0.0.dist-info/WHEEL
sl_shared_assets-7.0.0.dist-info/entry_points.txt
sl_shared_assets-7.0.0.dist-info/licenses/LICENSE
sl_shared_assets-7.0.0.dist-info/RECORD
