Metadata-Version: 2.4
Name: sl-shared-assets
Version: 7.0.0
Summary: Provides data acquisition and processing assets shared between Sun (NeuroAI) lab libraries.
Project-URL: Homepage, https://github.com/Sun-Lab-NBB/sl-shared-assets
Project-URL: Documentation, https://sl-shared-assets-api-docs.netlify.app/
Author: Ivan Kondratyev, Kushaan Gupta, Natalie Yeung
Maintainer-email: Ivan Kondratyev <ik278@cornell.edu>
License:                     GNU GENERAL PUBLIC LICENSE
License-File: LICENSE
Keywords: acquisition,assets,data,processing,server,sunlab
Classifier: Development Status :: 5 - Production/Stable
Classifier: Intended Audience :: Developers
Classifier: License :: OSI Approved :: GNU General Public License v3 or later (GPLv3+)
Classifier: Operating System :: OS Independent
Classifier: Programming Language :: Python :: 3.14
Classifier: Topic :: Scientific/Engineering
Classifier: Typing :: Typed
Requires-Python: <3.15,>=3.14
Requires-Dist: appdirs<2,>=1
Requires-Dist: ataraxis-base-utilities<6,>=5
Requires-Dist: ataraxis-data-structures<6,>=5
Requires-Dist: ataraxis-time<6,>=5
Requires-Dist: click<9,>=8
Requires-Dist: filelock<4,>=3
Requires-Dist: httpx<1,>=0.27
Requires-Dist: mcp<2,>=1
Requires-Dist: polars<2,>=1
Requires-Dist: pyarrow<23,>=22
Requires-Dist: tqdm<5,>=4
Requires-Dist: xxhash<4,>=3
Provides-Extra: dev
Requires-Dist: ataraxis-automation<8,>=7; extra == 'dev'
Requires-Dist: tox-uv<2,>=1; extra == 'dev'
Requires-Dist: tox<5,>=4; extra == 'dev'
Requires-Dist: types-appdirs<2,>=1; extra == 'dev'
Requires-Dist: types-filelock<4,>=3; extra == 'dev'
Requires-Dist: types-tqdm<5,>=4; extra == 'dev'
Requires-Dist: types-xxhash<4,>=3; extra == 'dev'
Requires-Dist: uv<1,>=0; extra == 'dev'
